fasteve/__init__.py
fasteve/applications.py
fasteve/core/__init__.py
fasteve/core/config.py
fasteve/core/utils.py
fasteve/endpoints/__init__.py
fasteve/endpoints/collections.py
fasteve/endpoints/documents.py
fasteve/endpoints/endpoints.py
fasteve/events.py
fasteve/io/__init__.py
fasteve/io/base.py
fasteve/io/mongo/__init__.py
fasteve/io/mongo/mongo.py
fasteve/io/mongo/utils.py
fasteve/io/sql/__init__.py
fasteve/io/sql/sql.py
fasteve/methods/__init__.py
fasteve/methods/common.py
fasteve/methods/delete.py
fasteve/methods/get.py
fasteve/methods/patch.py
fasteve/methods/post.py
fasteve/methods/put.py
fasteve/middleware/__init__.py
fasteve/middleware/cors.py
fasteve/middleware/resource.py
fasteve/model.py
fasteve/render.py
fasteve/resource.py
fasteve/utils.py
fasteve-0.2.3.dist-info/LICENSE
fasteve-0.2.3.dist-info/WHEEL
fasteve-0.2.3.dist-info/METADATA
fasteve-0.2.3.dist-info/RECORD
