Metadata-Version: 2.1
Name: fasteve
Version: 0.2.3
Summary: A simple and feature complete REST API framework designed for speed
Home-page: https://github.com/Wytamma/fasteve
License: BSD-3-Clause-Clear
Author: Wytamma Wirth
Author-email: wytamma.wirth@me.com
Requires-Python: >=3.6.2,<4.0
Classifier: License :: Other/Proprietary License
Classifier: Programming Language :: Python :: 3
Classifier: Programming Language :: Python :: 3.10
Classifier: Programming Language :: Python :: 3.7
Classifier: Programming Language :: Python :: 3.8
Classifier: Programming Language :: Python :: 3.9
Requires-Dist: email-validator (==1.1.1)
Requires-Dist: fastapi (>=0.70.1,<0.71.0)
Requires-Dist: motor (>=2.5.1,<3.0.0)
Requires-Dist: sqlmodel (>=0.0.6,<0.0.7)
Requires-Dist: uvicorn (>=0.16.0,<0.17.0)
Project-URL: Repository, https://github.com/Wytamma/fasteve
